pybezier/__init__.py
pybezier/bezier.py
pybezier/bezier_curve.py
pybezier/binomial.py
pybezier/composite_bezier.py
pybezier/composite_bezier_curve.py
pybezier-0.1.4.dist-info/licenses/LICENSE
pybezier-0.1.4.dist-info/METADATA
pybezier-0.1.4.dist-info/WHEEL
pybezier-0.1.4.dist-info/top_level.txt
pybezier-0.1.4.dist-info/RECORD
